setup.cfg
setup.py
retryable/__init__.py
retryable.egg-info/PKG-INFO
retryable.egg-info/SOURCES.txt
retryable.egg-info/dependency_links.txt
retryable.egg-info/top_level.txt