Metadata-Version: 1.0
Name: retryable
Version: 2016.3.11
Summary: Decorator for retrying python functions
Home-page: http://github.com/lnsybrd/retryable
Author: lnsy.brd
Author-email: lnsy.brd@gmail.com
License: UNKNOWN
Keywords: retry
Platform: UNKNOWN
